rdbms_op/__init__.py
rdbms_op/db_con.py
rdbms_op/db_con_func.py
rdbms_op/db_op_main.py
rdbms_op-0.0.6.dist-info/LICENSE
rdbms_op-0.0.6.dist-info/METADATA
rdbms_op-0.0.6.dist-info/WHEEL
rdbms_op-0.0.6.dist-info/top_level.txt
rdbms_op-0.0.6.dist-info/RECORD
